siepic_contradc/ContraDC.py
siepic_contradc/ContraDC_analysis.lsf
siepic_contradc/ContraDC_draw.lsf
siepic_contradc/ContraDC_simulate.lsf
siepic_contradc/ContraDC_simulatemodes.lsf
siepic_contradc/ContraDC_sparams.dat
siepic_contradc/MAIN_EME.lsf
siepic_contradc/__init__.py
siepic_contradc/contraDC.svg
siepic_contradc/lumerical_tools.py
siepic_contradc/materials.lsf
siepic_contradc/modules.py
siepic_contradc/scale_s_parameters.lsf
siepic_contradc/utils.py
siepic_contradc/write_sparams.lsf
siepic_contradc/Database/Target_wavelengths.txt
siepic_contradc/Database/neff/neff_1.txt
siepic_contradc/Database/neff/neff_2.txt
siepic_contradc/Database/neff/w1_w2_lambda.txt
siepic_contradc/Sparams/contraDC.svg
siepic_contradc/Sparams/scale_s_parameters.lsf
siepic_contradc/Sparams/write_sparams.lsf
siepic_contradc/Tutorial/SiN_1550_TE_w1_850nm_w2_1150nm_thickness_400nm.txt
siepic_contradc/Tutorial/Si_1550_TE_w1_440nm_w2_560nm_thickness_220nm.txt
siepic_contradc/Tutorial/__init__.py
siepic_contradc/Tutorial/examples.py
siepic_contradc/waveguide_coupler_mode/waveguide_coupler.lsf
siepic_contradc-0.1.5.dist-info/METADATA
siepic_contradc-0.1.5.dist-info/WHEEL
siepic_contradc-0.1.5.dist-info/top_level.txt
siepic_contradc-0.1.5.dist-info/RECORD
