Metadata-Version: 2.4
Name: siepic_contradc
Version: 0.1.5
Summary: Design of silicon photonic contra-directional grating-assisted couplers.
Author-email: Mustafa Hammood <mustafastation@gmail.com>
Project-URL: Homepage, https://github.com/SiEPIC/SiEPIC_Bragg_workshop
Project-URL: Issues, https://github.com/SiEPIC/SiEPIC_Bragg_workshop/issues
Classifier: Programming Language :: Python :: 3
Classifier: License :: OSI Approved :: MIT License
Classifier: Operating System :: OS Independent
Requires-Python: >=3.8
Requires-Dist: SiEPIC>=0.5.23
Requires-Dist: SiEPIC_EBeam_PDK
Requires-Dist: numpy
Requires-Dist: packaging
Requires-Dist: matplotlib
Requires-Dist: h5py
